fizzysearch/__init__.py
fizzysearch/__main__.py
fizzysearch/bloomtyper.py
fizzysearch/fts.py
fizzysearch/geo.py
fizzysearch/rdf2vec.py
fizzysearch/reader.py
fizzysearch/rewriting.py
fizzysearch-0.31.dist-info/licenses/LICENSE
fizzysearch-0.31.dist-info/METADATA
fizzysearch-0.31.dist-info/WHEEL
fizzysearch-0.31.dist-info/top_level.txt
fizzysearch-0.31.dist-info/RECORD
