Metadata-Version: 2.4
Name: fizzysearch
Version: 0.31
Summary: A SPARQL rewriter that performs enhanced searches
Author-email: Etienne Posthumus <ep@epoz.org>
License-Expression: MIT
Project-URL: Homepage, https://ise-fizkarlsruhe.github.io/fizzysearch/
Project-URL: Repository, https://github.com/ISE-FIZKarlsruhe/fizzysearch
Keywords: SPARQL,search,RDF,Linked Data
Requires-Python: >=3.10
License-File: LICENSE
Requires-Dist: bikidata>=0.3.5
Requires-Dist: rbloom==1.5.2
Requires-Dist: tree-sitter>=0.21.3
Dynamic: license-file
